paleta/__init__.py
paleta/api.py
paleta/color.py
paleta/image.py
paleta/metric.py
paleta/palette.py
paleta/version.py
paleta-1.0.1.dist-info/METADATA
paleta-1.0.1.dist-info/WHEEL
paleta-1.0.1.dist-info/top_level.txt
paleta-1.0.1.dist-info/zip-safe
paleta-1.0.1.dist-info/RECORD
